cpu/utils/encordings.v
`timescale 1ns/100ps

// ALU
`define ADD 5'b00000
`define SUB 5'b10000
`define SLL 5'b00001
`define SLT 5'b00010
`define SLTU 5'b00011
`define XOR 5'b00100
`define SRL 5'b00101
`define SRA 5'b10001
`define OR 5'b00110
`define AND 5'b00111
`define MUL 5'b01000
`define MULH 5'b01001
`define MULHSU 5'b01010
`define MULHU 5'b01011
`define DIV 5'b01100
`define DIVU 5'b01101
`define REM 5'b01110
`define REMU 5'b01111
`define FORWARD 5'b11xxx

`define I_TYPE = 3'b000
`define S_TYPE = 3'b001
`define B_TYPE = 3'b010
`define U_TYPE = 3'b011
`define J_TYPE = 3'b100

// Immediate Types
`define IMM_TYPE1 3'b000
`define IMM_TYPE2 3'b001
`define IMM_TYPE3 3'b010
`define IMM_TYPE4 3'b011
`define IMM_TYPE5 3'b100
`define IMM_TYPE6 3'b101

// Branch Types
`define BEQ 3'b000
`define BNE 3'b001
`define BLT 3'b100
`define BGE 3'b101
`define BLTU 3'b110
`define BGEU 3'b111
`define JAL_JALR 3'b010

// RV32I Base Integer Instructions Opcodes
`define OP_R_TYPE   7'b0110011
`define OP_I_TYPE   7'b0010011
`define OP_LOAD     7'b0000011
`define OP_STORE    7'b0100011
`define OP_BRANCH   7'b1100011
`define OP_JAL      7'b1101111
`define OP_JALR     7'b1100111
`define OP_LUI      7'b0110111
`define OP_AUIPC    7'b0010111
`define OP_SYSTEM   7'b1110011

cpu/ID_stage/sign_extender/sign_extender.v
`ifdef TB_RUN
    `include "../../utils/encordings.v"
`else
    `include "./utils/encordings.v"
`endif

`timescale 1ns/100ps

module sign_extender(inst, imm_sel, imm_ext);

input [31:0] inst;
input [3:0] imm_sel;
output reg [31:0] imm_ext;

wire [19:0] TYPE1, TYPE2;
wire [11:0] TYPE3, TYPE4, TYPE5;
wire [4:0] TYPE6;

// TODO: Check the combinations
assign TYPE1 = inst[31:12];
assign TYPE2 = inst[31:12];
assign TYPE3 = inst[31:20]; 
assign TYPE5 = {inst[31:25], inst[11:7]};
assign TYPE6 = inst[29:25]; 

always @(*) begin
    #2
    case (imm_sel[2:0])
        // TYPE 1 
        `IMM_TYPE1:
                imm_ext = {TYPE1, {12{1'b0}}};
        // TYPE 2 
        `IMM_TYPE2:
            if (imm_sel[3] == 1'b1) 
                imm_ext = {{11{1'b0}}, TYPE2, 1'b0};
            else
                imm_ext = {{11{inst[31]}}, inst[31], inst[19:12], inst[20], inst[30:21], 1'b0}; //{{11{TYPE2[19]}}, TYPE2, 1'b0};
        // TYPE 3 
        `IMM_TYPE3:
            if (imm_sel[3] == 1'b1) 
                imm_ext = {{20{1'b0}}, TYPE3};
            else
                imm_ext = {{20{TYPE3[11]}}, TYPE3};
        // TYPE 4 
        `IMM_TYPE4:
            if (imm_sel[3] == 1'b1) 
                imm_ext = {{20{1'b0}}, inst[31], inst[7], inst[30:25], inst[11:8], 1'b0};
            else
                imm_ext = {{20{inst[31]}}, inst[31], inst[7], inst[30:25], inst[11:8], 1'b0};
        // TYPE 5 
        `IMM_TYPE5:
            if (imm_sel[3] == 1'b1) 
                imm_ext = {{20{1'b0}}, TYPE5};
            else
                imm_ext = {{20{TYPE5[11]}}, TYPE5};
        // TYPE 6 
        `IMM_TYPE6:
            imm_ext = {{27{1'b0}}, TYPE6};
    endcase
end



endmodule

cpu/ID_stage/sign_extender/sign_extender_tb.v
`define TB_RUN
`include "sign_extender.v"

`timescale 1ns/100ps

module sign_extender_tb;

    // Inputs
    reg [31:0] inst;
    reg [3:0] imm_sel;

    // Outputs
    wire [31:0] imm_ext;

    // Instantiate the sign_extender module
    sign_extender uut (
        .inst(inst),
        .imm_sel(imm_sel),
        .imm_ext(imm_ext)
    );

    // Testbench logic
    initial begin
        // Open a file for logging
        $dumpfile("tb_sign_extender.vcd");
        $dumpvars(0, sign_extender_tb);

        $monitor("Time: %d | IMM_SEL: %b | IMM_EXT: %h", $time, imm_sel, imm_ext);

        // Test case 1: IMM_TYPE1 (U-type immediate)
        inst = 32'hFFFFF123; // Example U-type instruction
        imm_sel = `IMM_TYPE1;
        /*#1*/0;
        $display($time, "IMM_TYPE1: inst = %h, imm_ext = %h", inst, imm_ext);

        // Test case 2: IMM_TYPE2 (J-type immediate, signed)
        inst = 32'hF1234567; // Example J-type instruction
        imm_sel = `IMM_TYPE2;
        /*#1*/0;
        $display($time, "IMM_TYPE2 (signed): inst = %h, imm_ext = %h", inst, imm_ext);

        // Test case 3: IMM_TYPE2 (J-type immediate, unsigned)
        inst = 32'hF1234567; // Example J-type instruction
        imm_sel = {1'b1, `IMM_TYPE2}; // Set imm_sel[3] = 1 for unsigned
        /*#1*/0;
        $display($time, "IMM_TYPE2 (unsigned): inst = %h, imm_ext = %h", inst, imm_ext);

        // Test case 4: IMM_TYPE3 (I-type immediate, signed)
        inst = 32'hF1234567; // Example I-type instruction
        imm_sel = `IMM_TYPE3;
        /*#1*/0;
        $display($time, "IMM_TYPE3 (signed): inst = %h, imm_ext = %h", inst, imm_ext);

        // Test case 5: IMM_TYPE3 (I-type immediate, unsigned)
        inst = 32'hF1234567; // Example I-type instruction
        imm_sel = {1'b1, `IMM_TYPE3}; // Set imm_sel[3] = 1 for unsigned
        /*#1*/0;
        $display($time, "IMM_TYPE3 (unsigned): inst = %h, imm_ext = %h", inst, imm_ext);

        // Test case 6: IMM_TYPE4 (B-type immediate, signed)
        inst = 32'hF1234567; // Example B-type instruction
        imm_sel = `IMM_TYPE4;
        /*#1*/0;
        $display($time, "IMM_TYPE4 (signed): inst = %h, imm_ext = %h", inst, imm_ext);

        // Test case 7: IMM_TYPE4 (B-type immediate, unsigned)
        inst = 32'hF1234567; // Example B-type instruction
        imm_sel = {1'b1, `IMM_TYPE4}; // Set imm_sel[3] = 1 for unsigned
        /*#1*/0;
        $display($time, "IMM_TYPE4 (unsigned): inst = %h, imm_ext = %h", inst, imm_ext);

        // Test case 8: IMM_TYPE5 (S-type immediate, signed)
        inst = 32'hF1234567; // Example S-type instruction
        imm_sel = `IMM_TYPE5;
        /*#1*/0;
        $display($time, "IMM_TYPE5 (signed): inst = %h, imm_ext = %h", inst, imm_ext);

        // Test case 9: IMM_TYPE5 (S-type immediate, unsigned)
        inst = 32'hF1234567; // Example S-type instruction
        imm_sel = {1'b1, `IMM_TYPE5}; // Set imm_sel[3] = 1 for unsigned
        /*#1*/0;
        $display($time, "IMM_TYPE5 (unsigned): inst = %h, imm_ext = %h", inst, imm_ext);

        // Test case 10: IMM_TYPE6 (CSR-type immediate)
        inst = 32'hF1234567; // Example CSR-type instruction
        imm_sel = `IMM_TYPE6;
        /*#1*/0;
        $display($time, "IMM_TYPE6: inst = %h, imm_ext = %h", inst, imm_ext);

        // End simulation
        $finish;
    end

endmodule

cpu/ID_stage/sign_extender/tb_sign_extender.vcd
$date
	Sun Feb 02 12:35:31 2025
$end
$version
	Icarus Verilog
$end
$timescale
	100ps
$end
$scope module sign_extender_tb $end
$var wire 32 ! imm_ext [31:0] $end
$var reg 4 " imm_sel [3:0] $end
$var reg 32 # inst [31:0] $end
$scope module uut $end
$var wire 4 $ imm_sel [3:0] $end
$var wire 32 % inst [31:0] $end
$var wire 5 & TYPE6 [4:0] $end
$var wire 12 ' TYPE5 [11:0] $end
$var wire 12 ( TYPE3 [11:0] $end
$var wire 20 ) TYPE2 [19:0] $end
$var wire 20 * TYPE1 [19:0] $end
$var reg 32 + imm_ext [31:0] $end
$upscope $end
$upscope $end
$enddefinitions $end
$comment Show the parameter values. $end
$dumpall
$end
#0
$dumpvars
bx +
b11111111111111111111 *
b11111111111111111111 )
b111111111111 (
b111111100010 '
b11111 &
b11111111111111111111000100100011 %
b0 $
b11111111111111111111000100100011 #
b0 "
bx !
$end
/*#2*/0
b11111111111111111111000000000000 !
b11111111111111111111000000000000 +
/*#1*/00
b11110001001000110100 *
b11110001001000110100 )
b111100010010 (
b111100001010 '
b11000 &
b1 "
b1 $
b11110001001000110100010101100111 #
b11110001001000110100010101100111 %
/*#1*/20
b11111111111100110100011100010010 !
b11111111111100110100011100010010 +
/*#2*/00
b1001 "
b1001 $
/*#2*/20
b111100010010001101000 !
b111100010010001101000 +
/*#3*/00
b10 "
b10 $
/*#3*/20
b11111111111111111111111100010010 !
b11111111111111111111111100010010 +
#400
b1010 "
b1010 $
#420
b111100010010 !
b111100010010 +
#500
b11 "
b11 $
#520
b11111111111111111111011100001010 !
b11111111111111111111011100001010 +
#600
b1011 "
b1011 $
#620
b1011100001010 !
b1011100001010 +
#700
b100 "
b100 $
#720
b11111111111111111111111100001010 !
b11111111111111111111111100001010 +
#800
b1100 "
b1100 $
#820
b111100001010 !
b111100001010 +
#900
b101 "
b101 $
#920
b11000 !
b11000 +
/*#1*/000
